{
  "menu": [
    {
      "img": "img/tabs/vegy.jpg",
      "altimg": "vegy",
      "title": "Меню 'Фитнес'",
      "descr": "Меню 'Фитнес' - это новый подход к приготовлению блюд: больше свежих овощей и фруктов. Продукт активных и здоровых людей. Это абсолютно новый продукт с оптимальной ценой и высоким качеством!",
      "price": 9
    },
    {
      "img": "img/tabs/post.jpg",
      "altimg": "post",
      "title": "Меню 'Постное'",
      "descr": "Меню 'Постное' - это тщательный подбор ингредиентов: полное отсутствие продуктов животного происхождения, молоко из миндаля, овса, кокоса или гречки, правильное количество белков за счет тофу и импортных вегетарианских стейков.",
      "price": 14
    },
    {
      "img": "img/tabs/elite.jpg",
      "altimg": "elite",
      "title": "Меню 'Премиум'",
      "descr": "В меню 'Премиум' мы используем не только красивый дизайн упаковки, но и качественное исполнение блюд. Красная рыба, морепродукты, фрукты - ресторанное меню без похода в ресторан!",
      "price": 21
    }
  ],
  "requests": [
    {
      "name": "Артур",
      "phone": " +37369304992",
      "id": 1
    },
    {
      "name": "Артур",
      "phone": "37379270401",
      "id": 2
    },
    {
      "name": "eqw",
      "phone": "eqw",
      "id": 3
    },
    {
      "name": "xzxz",
      "phone": "xzxxz",
      "id": 4
    },
    {
      "name": "ewq",
      "phone": "ewq",
      "id": 5
    },
    {
      "name": "ewq",
      "phone": "ewq",
      "id": 6
    },
    {
      "name": "31",
      "phone": "ewq",
      "id": 7
    },
    {
      "name": "ewqewq",
      "phone": "ewq",
      "id": 8
    },
    {
      "name": "ewq",
      "phone": "e",
      "id": 9
    },
    {
      "name": "1e",
      "phone": "ewq",
      "id": 10
    },
    {
      "name": "ewq",
      "phone": "eq",
      "id": 11
    },
    {
      "name": "ewq",
      "phone": "qew",
      "id": 12
    },
    {
      "name": "ewq",
      "phone": "ewq",
      "id": 13
    },
    {
      "name": "dwq",
      "phone": "dwq",
      "id": 14
    },
    {
      "name": "ewq",
      "phone": "ewq",
      "id": 15
    },
    {
      "name": "dwq",
      "phone": "dwq",
      "id": 16
    },
    {
      "name": "ewq",
      "phone": "eqw",
      "id": 17
    },
    {
      "name": "wq",
      "phone": "wq",
      "id": 18
    },
    {
      "name": "wq",
      "phone": "wq",
      "id": 19
    },
    {
      "name": "eqw",
      "phone": "ewq",
      "id": 20
    },
    {
      "name": "ee21e12e",
      "phone": "12e12e12e12e",
      "id": 21
    },
    {
      "name": "1d2",
      "phone": "dwq",
      "id": 22
    },
    {
      "name": "ewq",
      "phone": "weq",
      "id": 23
    },
    {
      "name": "dwq",
      "phone": "ewq",
      "id": 24
    },
    {
      "name": "dwq",
      "phone": "dqw",
      "id": 25
    },
    {
      "name": "ewq",
      "phone": "qw",
      "id": 26
    },
    {
      "name": "fg",
      "phone": "gfd",
      "id": 27
    },
    {
      "name": "eqw",
      "phone": "qweqw",
      "id": 28
    },
    {
      "name": "qweqwe",
      "phone": "ewq",
      "id": 29
    }
  ]
}